km3dia/DOM_integration_summary.py
km3dia/__init__.py
km3dia/core.py
km3dia/tools.py
km3dia/version.py
km3dia/cli/generate_opt.py
km3dia-0.2.6.dist-info/LICENSE
km3dia-0.2.6.dist-info/METADATA
km3dia-0.2.6.dist-info/WHEEL
km3dia-0.2.6.dist-info/entry_points.txt
km3dia-0.2.6.dist-info/top_level.txt
km3dia-0.2.6.dist-info/RECORD
