Metadata-Version: 2.1
Name: km3dia
Version: 0.2.6
Summary: Python module providing access to DIA DB information.
Home-page: https://git.km3net.de/km3py/km3dia
Author: Valentin Pestel
Author-email: vpestel@km3net.de
License: UNKNOWN
Platform: any
Classifier: Intended Audience :: Developers
Classifier: Intended Audience :: Science/Research
Classifier: Programming Language :: Python
Requires-Python: >=3.6
Requires-Dist: setuptools-scm
Requires-Dist: km3db
Requires-Dist: pandas
Provides-Extra: dev
Requires-Dist: black ; extra == 'dev'
Requires-Dist: matplotlib ; extra == 'dev'
Requires-Dist: numpydoc ; extra == 'dev'
Requires-Dist: pillow ; extra == 'dev'
Requires-Dist: pytest ; extra == 'dev'
Requires-Dist: pytest-cov ; extra == 'dev'
Requires-Dist: pytest-flake8 ; extra == 'dev'
Requires-Dist: pytest-pylint ; extra == 'dev'
Requires-Dist: pytest-watch ; extra == 'dev'
Requires-Dist: sphinx ; extra == 'dev'
Requires-Dist: sphinx-autoapi ; extra == 'dev'
Requires-Dist: sphinx-gallery (>=0.1.12) ; extra == 'dev'
Requires-Dist: sphinx-rtd-theme ; extra == 'dev'
Requires-Dist: sphinxcontrib-versioning ; extra == 'dev'
Requires-Dist: wheel ; extra == 'dev'
